risklabs/analysis_models.py
risklabs/client.py
risklabs/data.py
risklabs/engine.py
risklabs/models.py
risklabs/reporting.py
risklabs/api/server.py
risklabs/static/index.html
risklabs-0.2.4.dist-info/METADATA
risklabs-0.2.4.dist-info/WHEEL
risklabs-0.2.4.dist-info/RECORD
