Metadata-Version: 2.4
Name: risklabs
Version: 0.2.4
Summary: Decision-Risk & Robustness Simulator by Allostan Labs
Author-email: Antigravity <antigravity@gemini.com>
Requires-Python: >=3.11
Requires-Dist: numpy>=1.26.0
Requires-Dist: pandas>=2.2.0
Requires-Dist: pydantic-settings>=2.1.0
Requires-Dist: pydantic>=2.6.0
Requires-Dist: yfinance>=0.2.36
Provides-Extra: dev
Requires-Dist: black>=24.1.0; extra == 'dev'
Requires-Dist: httpx>=0.26.0; extra == 'dev'
Requires-Dist: mypy>=1.8.0; extra == 'dev'
Requires-Dist: pytest>=8.0.0; extra == 'dev'
Requires-Dist: ruff>=0.1.15; extra == 'dev'
Provides-Extra: server
Requires-Dist: fastapi>=0.109.0; extra == 'server'
Requires-Dist: python-multipart>=0.0.9; extra == 'server'
Requires-Dist: uvicorn>=0.27.0; extra == 'server'
